pyrameter/__init__.py
pyrameter/graphing.py
pyrameter/optimizer.py
pyrameter/reproducibility.py
pyrameter/scaling.py
pyrameter/searchspace.py
pyrameter/specification.py
pyrameter/trial.py
pyrameter/utils.py
pyrameter/backend/__init__.py
pyrameter/backend/base.py
pyrameter/backend/local.py
pyrameter/backend/mongo.py
pyrameter/backend/sqlite.py
pyrameter/domains/__init__.py
pyrameter/domains/base.py
pyrameter/domains/conditional.py
pyrameter/domains/constant.py
pyrameter/domains/continuous.py
pyrameter/domains/discrete.py
pyrameter/domains/exhaustive.py
pyrameter/domains/joint.py
pyrameter/domains/linked.py
pyrameter/domains/repeated.py
pyrameter/domains/sequence.py
pyrameter/methods/__init__.py
pyrameter/methods/bayes.py
pyrameter/methods/hom.py
pyrameter/methods/method.py
pyrameter/methods/ncqs.py
pyrameter/methods/pso.py
pyrameter/methods/random_search.py
pyrameter/methods/smac.py
pyrameter/methods/tpe.py
pyrameter-0.3.5.post3.dist-info/METADATA
pyrameter-0.3.5.post3.dist-info/WHEEL
pyrameter-0.3.5.post3.dist-info/top_level.txt
pyrameter-0.3.5.post3.dist-info/RECORD
