Metadata-Version: 2.1
Name: pyrameter
Version: 0.3.5.post3
Summary: Structure, sample, and savor hyperparameter searches
Home-page: https://github.com/jeffkinnison/pyrameter
Author: Jeff Kinnison
Author-email: jkinniso@nd.edu
Keywords: machine_learning hyperparameters
Classifier: Development Status :: 4 - Beta
Classifier: Intended Audience :: Science/Research
Classifier: License :: OSI Approved :: MIT License
Classifier: Topic :: Scientific/Engineering :: Artificial Intelligence
Classifier: Programming Language :: Python :: 3
Classifier: Programming Language :: Python :: 3.6
Classifier: Programming Language :: Python :: 3.7
Classifier: Programming Language :: Python :: 3.8
Classifier: Operating System :: POSIX
Classifier: Operating System :: Unix
Requires-Dist: dill
Requires-Dist: matplotlib
Requires-Dist: numpy
Requires-Dist: pandas
Requires-Dist: pymongo
Requires-Dist: scipy
Requires-Dist: scikit-learn
Requires-Dist: six
